diffrax/__init__.py
diffrax/_adjoint.py
diffrax/_autocitation.py
diffrax/_custom_types.py
diffrax/_event.py
diffrax/_global_interpolation.py
diffrax/_heuristics.py
diffrax/_integrate.py
diffrax/_local_interpolation.py
diffrax/_misc.py
diffrax/_path.py
diffrax/_progress_meter.py
diffrax/_saveat.py
diffrax/_solution.py
diffrax/_term.py
diffrax/_typing.py
diffrax/py.typed
diffrax/_brownian/__init__.py
diffrax/_brownian/base.py
diffrax/_brownian/path.py
diffrax/_brownian/tree.py
diffrax/_root_finder/__init__.py
diffrax/_root_finder/_verychord.py
diffrax/_root_finder/_with_tols.py
diffrax/_solver/__init__.py
diffrax/_solver/align.py
diffrax/_solver/base.py
diffrax/_solver/bosh3.py
diffrax/_solver/dopri5.py
diffrax/_solver/dopri8.py
diffrax/_solver/euler.py
diffrax/_solver/euler_heun.py
diffrax/_solver/foster_langevin_srk.py
diffrax/_solver/heun.py
diffrax/_solver/implicit_euler.py
diffrax/_solver/kencarp3.py
diffrax/_solver/kencarp4.py
diffrax/_solver/kencarp5.py
diffrax/_solver/kvaerno3.py
diffrax/_solver/kvaerno4.py
diffrax/_solver/kvaerno5.py
diffrax/_solver/leapfrog_midpoint.py
diffrax/_solver/midpoint.py
diffrax/_solver/milstein.py
diffrax/_solver/quicsort.py
diffrax/_solver/ralston.py
diffrax/_solver/reversible_heun.py
diffrax/_solver/runge_kutta.py
diffrax/_solver/sea.py
diffrax/_solver/semi_implicit_euler.py
diffrax/_solver/shark.py
diffrax/_solver/shark_general.py
diffrax/_solver/should.py
diffrax/_solver/sil3.py
diffrax/_solver/slowrk.py
diffrax/_solver/spark.py
diffrax/_solver/sra1.py
diffrax/_solver/srk.py
diffrax/_solver/tsit5.py
diffrax/_step_size_controller/__init__.py
diffrax/_step_size_controller/base.py
diffrax/_step_size_controller/clip.py
diffrax/_step_size_controller/constant.py
diffrax/_step_size_controller/pid.py
diffrax-0.7.0.dist-info/METADATA
diffrax-0.7.0.dist-info/WHEEL
diffrax-0.7.0.dist-info/licenses/LICENSE
diffrax-0.7.0.dist-info/RECORD
