Metadata-Version: 2.4
Name: diffrax
Version: 0.7.0
Summary: GPU+autodiff-capable ODE/SDE/CDE solvers written in JAX.
Project-URL: repository, https://github.com/patrick-kidger/diffrax
Author-email: Patrick Kidger <contact@kidger.site>
License:                                  Apache License
License-File: LICENSE
Keywords: deep-learning,differential-equations,diffrax,dynamical-systems,equinox,jax,neural-differential-equations
Classifier: Development Status :: 3 - Alpha
Classifier: Intended Audience :: Developers
Classifier: Intended Audience :: Financial and Insurance Industry
Classifier: Intended Audience :: Information Technology
Classifier: Intended Audience :: Science/Research
Classifier: License :: OSI Approved :: Apache Software License
Classifier: Natural Language :: English
Classifier: Programming Language :: Python :: 3
Classifier: Topic :: Scientific/Engineering :: Artificial Intelligence
Classifier: Topic :: Scientific/Engineering :: Information Analysis
Classifier: Topic :: Scientific/Engineering :: Mathematics
Requires-Python: <4.0,>=3.10
Requires-Dist: equinox>=0.11.10
Requires-Dist: jax>=0.4.38
Requires-Dist: jaxtyping>=0.2.24
Requires-Dist: lineax>=0.0.5
Requires-Dist: optimistix>=0.0.10
Requires-Dist: typing-extensions>=4.5.0
Requires-Dist: wadler-lindig>=0.1.1
